canonical_sphinx/__init__.py
canonical_sphinx/_version.py
canonical_sphinx/config.py
canonical_sphinx/theme/__init__.py
canonical_sphinx/theme/theme.conf
canonical_sphinx/theme/PDF/Canonical-logo-4x.png
canonical_sphinx/theme/PDF/LICENCE.txt
canonical_sphinx/theme/PDF/Ubuntu-B.ttf
canonical_sphinx/theme/PDF/Ubuntu-R.ttf
canonical_sphinx/theme/PDF/Ubuntu-RI.ttf
canonical_sphinx/theme/PDF/UbuntuMono-B.ttf
canonical_sphinx/theme/PDF/UbuntuMono-R.ttf
canonical_sphinx/theme/PDF/UbuntuMono-RI.ttf
canonical_sphinx/theme/PDF/front-page-light.pdf
canonical_sphinx/theme/PDF/latex_elements_template.txt
canonical_sphinx/theme/PDF/normal-page-footer.pdf
canonical_sphinx/theme/static/404.svg
canonical_sphinx/theme/static/custom.css
canonical_sphinx/theme/static/favicon.png
canonical_sphinx/theme/static/furo_colors.css
canonical_sphinx/theme/static/github_issue_links.css
canonical_sphinx/theme/static/github_issue_links.js
canonical_sphinx/theme/static/header-nav.js
canonical_sphinx/theme/static/header.css
canonical_sphinx/theme/static/tag.png
canonical_sphinx/theme/templates/404.html
canonical_sphinx/theme/templates/base.html
canonical_sphinx/theme/templates/footer.html
canonical_sphinx/theme/templates/header.html
canonical_sphinx/theme/templates/page.html
canonical_sphinx/theme/templates/components/edit-this-page.html
canonical_sphinx/theme/templates/components/view-this-page.html
canonical_sphinx/theme/templates/sidebar/search.html
canonical_sphinx-0.5.2.dist-info/LICENSE
canonical_sphinx-0.5.2.dist-info/METADATA
canonical_sphinx-0.5.2.dist-info/WHEEL
canonical_sphinx-0.5.2.dist-info/entry_points.txt
canonical_sphinx-0.5.2.dist-info/top_level.txt
canonical_sphinx-0.5.2.dist-info/RECORD
